tor/__init__.py
tor/base.py
tor/movies.py
pandelyon_theonesdk-0.1.0.dist-info/LICENSE
pandelyon_theonesdk-0.1.0.dist-info/WHEEL
pandelyon_theonesdk-0.1.0.dist-info/METADATA
pandelyon_theonesdk-0.1.0.dist-info/RECORD
