Metadata-Version: 2.1
Name: pandelyon-theonesdk
Version: 0.1.0
Summary: Prototype SDK built against The One API
Home-page: https://github.com/adyates/adyates-sdk
License: MIT
Author: A Y
Author-email: github@pandelyon.com
Requires-Python: >=3.11,<4.0
Classifier: License :: OSI Approved :: MIT License
Classifier: Programming Language :: Python :: 3
Classifier: Programming Language :: Python :: 3.11
Requires-Dist: requests (>=2.28.2,<3.0.0)
Project-URL: Repository, https://github.com/adyates/adyates-sdk
